{
  "videos": [
    {
      "title": "How do you break from inner loop",
      "description": "Break from inner loop in JavaScript using labels",
      "image": "/images/howDoYouBreakFromInnerLoop.jpeg",
      "tags": ["loops", "label"],
      "urls": [
        {
          "icon": "fab fa-facebook",
          "url": "https://www.facebook.com/reel/479200971476853"
        },
        {
          "icon": "fab fa-instagram",
          "url": "https://www.instagram.com/reel/C9Jv5sPtauZ/"
        },
        {
          "icon": "fab fa-threads",
          "url": "https://www.threads.net/@hacky.js/post/C9rnQQpNgpQ"
        },
        {
          "icon": "fab fa-youtube",
          "url": "https://www.youtube.com/shorts/E7Qx5tX6qn8"
        },
        {
          "icon": "fab fa-x-twitter",
          "url": "https://x.com/pr0h0_me/status/1810203969592930489"
        },
        {
          "icon": "fab fa-tiktok",
          "url": "https://www.tiktok.com/@hacky.js/video/7389018569536851206"
        }
      ]
    },
    {
      "title": "Edit search parameters like a real senior",
      "description": "Use URLSearchParams to edit search parameters in the URL",
      "image": "/images/urlSearchParams.jpeg",
      "tags": ["url", "search"],
      "urls": [
        {
          "icon": "fab fa-instagram",
          "url": "https://www.instagram.com/reel/C9LZ6umtbjG/"
        },
        {
          "icon": "fab fa-youtube",
          "url": "https://www.youtube.com/shorts/6ZABs37o4Vg"
        },
        {
          "icon": "fab fa-x-twitter",
          "url": "https://x.com/pr0h0_me/status/1810439688311996837"
        }
      ]
    },
    {
      "title": "Don't waste time assigning properties manually ",
      "description": "Use Object.assign() or spread operator to assign properties to an object",
      "image": "/images/objectAssign.jpeg",
      "tags": ["objects", "spread"],
      "urls": [
        {
          "icon": "fab fa-instagram",
          "url": "https://www.instagram.com/reel/C9Nt77eNKjg/"
        },
        {
          "icon": "fab fa-youtube",
          "url": "https://www.youtube.com/shorts/ej78TKK4bN4"
        },
        {
          "icon": "fab fa-x-twitter",
          "url": "https://x.com/pr0h0_me/status/1810764729952129481"
        },
        {
          "icon": "fab fa-tiktok",
          "url": "https://www.tiktok.com/@hacky.js/video/7389725874632854790"
        }
      ]
    },
    {
      "title": "Define custom property on any class or object in javascript",
      "description": "Use Object.defineProperty() to define custom property on any class or object in javascript",
      "image": "/images/defineProperty.jpeg",
      "tags": ["objects", "defineProperty"],
      "urls": [
        {
          "icon": "fab fa-instagram",
          "url": "https://www.instagram.com/reel/C9TKppXN9hh/"
        },
        {
          "icon": "fab fa-youtube",
          "url": "https://www.youtube.com/shorts/L-F5b7AF9Jc"
        },
        {
          "icon": "fab fa-x-twitter",
          "url": "https://x.com/pr0h0_me/status/1811532425081823741"
        },
        {
          "icon": "fab fa-tiktok",
          "url": "https://www.tiktok.com/@hacky.js/video/7390512378577718533"
        }
      ]
    },
    {
      "title": "Set CSS variables using Javascript #programming",
      "description": "Set CSS variables from Javascript using documentElement.style.setProperty()",
      "image": "/images/setProperty.jpeg",
      "tags": ["css", "variables"],
      "urls": [
        {
          "icon": "fab fa-instagram",
          "url": "https://www.instagram.com/reel/C9aooiqNSf2/"
        },
        {
          "icon": "fab fa-youtube",
          "url": "https://www.youtube.com/shorts/ZXGmKozGeQo"
        },
        {
          "icon": "fab fa-x-twitter",
          "url": "https://x.com/pr0h0_me/status/1812585251329458301"
        },
        {
          "icon": "fab fa-tiktok",
          "url": "https://www.tiktok.com/@hacky.js/video/7391589693889973509"
        },
        {
          "icon": "fab fa-codepen",
          "url": "https://codepen.io/pr0h0/details/XWLbLBw"
        }
      ]
    },
    {
      "title": "Stop throwing generic error in javascript",
      "description": "Throw error in javascript using custom error class and handle it properly",
      "image": "/images/customErrors.jpeg",
      "tags": ["errors", "custom"],
      "urls": [
        {
          "icon": "fab fa-instagram",
          "url": "https://www.instagram.com/reel/C9dXNyvt3y7/"
        },
        {
          "icon": "fab fa-youtube",
          "url": "https://www.youtube.com/shorts/UTy13-0SbRc"
        },
        {
          "icon": "fab fa-x-twitter",
          "url": "https://x.com/pr0h0_me/status/1812968606457540780"
        },
        {
          "icon": "fab fa-tiktok",
          "url": "https://www.tiktok.com/@hacky.js/video/7391983658715974917"
        }
      ]
    },
    {
      "title": "Do you know this setInterval hack in JS",
      "description": "Use custom setInterval wrapper to make it more efficient and easy to use",
      "image": "/images/setInterval.jpeg",
      "tags": ["setInterval", "wrapper"],
      "urls": [
        {
          "icon": "fab fa-instagram",
          "url": "https://www.instagram.com/reel/C9g7_nftdW1/"
        },
        {
          "icon": "fab fa-youtube",
          "url": "https://www.youtube.com/shorts/V4jNgTlI2Ls"
        },
        {
          "icon": "fab fa-x-twitter",
          "url": "https://x.com/pr0h0_me/status/1813469961798443381"
        },
        {
          "icon": "fab fa-tiktok",
          "url": "https://www.tiktok.com/@hacky.js/video/7392496726734671109"
        }
      ]
    },
    {
      "title": "Learn the difference between basic and complex types",
      "description": "Reference types and primitive types in JavaScript and how they are used",
      "image": "/images/referenceTypes.jpeg",
      "tags": ["reference", "primitive"],
      "urls": [
        {
          "icon": "fab fa-instagram",
          "url": "https://www.instagram.com/reel/C9iinZOtulI/"
        },
        {
          "icon": "fab fa-youtube",
          "url": "https://www.youtube.com/watch?v=Ye_hOyU_Pw8"
        },
        {
          "icon": "fab fa-x-twitter",
          "url": "https://x.com/pr0h0_me/status/1813697865128321205"
        },
        {
          "icon": "fab fa-tiktok",
          "url": "https://www.tiktok.com/@hacky.js/video/7392726603958095109"
        }
      ]
    },
    {
      "title": "Generate image from HTML code",
      "description": "Generate image from HTML code using HTML2canvas and download it",
      "image": "/images/html2canvas.jpeg",
      "tags": ["html2canvas", "image"],
      "urls": [
        {
          "icon": "fab fa-instagram",
          "url": "https://www.instagram.com/reel/C9nRKVptU0G/"
        },
        {
          "icon": "fab fa-facebook",
          "url": "https://www.facebook.com/reel/1424207714954672"
        },
        {
          "icon": "fab fa-youtube",
          "url": "https://www.youtube.com/shorts/dIthyk3VPdU"
        },
        {
          "icon": "fab fa-x-twitter",
          "url": "https://x.com/pr0h0_me/status/1814360309814940077"
        },
        {
          "icon": "fab fa-tiktok",
          "url": "https://www.tiktok.com/@hacky.js/video/7393608117402995974"
        },
        {
          "icon": "fab fa-codepen",
          "url": "https://codepen.io/pr0h0/details/WNqwGGM"
        }
      ]
    },
    {
      "title": "Create custom event emitter or use HTML Element",
      "description": "Create custom event emitter or reuse HTML Element to emit custom events",
      "image": "/images/customEmitter.jpeg",
      "tags": ["events", "emitter", "HTML"],
      "urls": [
        {
          "icon": "fab fa-instagram",
          "url": "https://www.instagram.com/reel/C9qfU9PtEuX/"
        },
        {
          "icon": "fab fa-facebook",
          "url": "https://www.facebook.com/reel/1286268109424431"
        },
        {
          "icon": "fab fa-threads",
          "url": "https://www.threads.net/@hacky.js/post/C9qipLkNrpP"
        },
        {
          "icon": "fab fa-youtube",
          "url": "https://www.youtube.com/shorts/AgDW5k9EJPE"
        },
        {
          "icon": "fab fa-x-twitter",
          "url": "https://x.com/pr0h0_me/status/1814818203358363716"
        },
        {
          "icon": "fab fa-tiktok",
          "url": "https://www.tiktok.com/@hacky.js/video/7393875439585987846"
        },
        {
          "icon": "fab fa-codepen",
          "url": "https://codepen.io/pr0h0/details/ExBKRem"
        }
      ]
    },
    {
      "title": "Create dynamic background using SVG in CSS",
      "description": "Designing SVG backgrounds in CSS for websites",
      "image": "/images/svgBackground.jpeg",
      "tags": ["css", "svg", "background"],
      "urls": [
        {
          "icon": "fab fa-instagram",
          "url": "https://www.instagram.com/p/C9s1JOKujD5/"
        },
        {
          "icon": "fab fa-facebook",
          "url": "https://www.facebook.com/reel/1039832831050464"
        },
        {
          "icon": "fab fa-threads",
          "url": "https://www.threads.net/@hacky.js/post/C9s1u2rMuAe"
        },
        {
          "icon": "fab fa-youtube",
          "url": "https://www.youtube.com/shorts/2CO4o1wA5zA"
        },
        {
          "icon": "fab fa-x-twitter",
          "url": "https://x.com/pr0h0_me/status/1815143730061685047"
        },
        {
          "icon": "fab fa-tiktok",
          "url": "https://www.tiktok.com/@hacky.js/video/7394207765293665542"
        },
        {
          "icon": "fab fa-codepen",
          "url": "https://codepen.io/pr0h0/pen/gONrJPe"
        }
      ]
    },
    {
      "title": "JavaScript Console Tricks for Debugging",
      "description": "Useful console tricks for debugging in JavaScript",
      "image": "/images/consoleTricks.jpeg",
      "tags": ["console", "log", "debugging"],
      "urls": [
        {
          "icon": "fab fa-instagram",
          "url": "https://www.instagram.com/reel/C9vKBWRMTn1/"
        },
        {
          "icon": "fab fa-facebook",
          "url": "https://www.facebook.com/reel/461935566694363"
        },
        {
          "icon": "fab fa-threads",
          "url": "https://www.threads.net/@hacky.js/post/C9vLhaMMDDv"
        },
        {
          "icon": "fab fa-youtube",
          "url": "https://youtube.com/shorts/7fwbgYITlro"
        },
        {
          "icon": "fab fa-x-twitter",
          "url": "https://x.com/pr0h0_me/status/1815473050424590716"
        },
        {
          "icon": "fab fa-tiktok",
          "url": "https://www.tiktok.com/@hacky.js/video/7394543829065518342"
        }
      ]
    },
    {
      "title": "Resize any image using canvas in JavaScript",
      "description": "Resize images before upload or display using canvas in JavaScript",
      "image": "/images/resizeAnyImage.jpeg",
      "tags": ["canvas", "image", "resize"],
      "urls": [
        {
          "icon": "fab fa-instagram",
          "url": "https://www.instagram.com/reel/C9xyBfQtmoo/"
        },
        {
          "icon": "fab fa-facebook",
          "url": "https://www.facebook.com/reel/407414508435006"
        },
        {
          "icon": "fab fa-threads",
          "url": "https://www.threads.net/@hacky.js/post/C9xzjQxRvh1"
        },
        {
          "icon": "fab fa-youtube",
          "url": "https://youtube.com/shorts/iAIgwQwMySE"
        },
        {
          "icon": "fab fa-x-twitter",
          "url": "https://x.com/pr0h0_me/status/1815842407096975371"
        },
        {
          "icon": "fab fa-tiktok",
          "url": "https://www.tiktok.com/@hacky.js/video/7394921974138522885"
        },
        {
          "icon": "fab fa-codepen",
          "url": "https://codepen.io/pr0h0/details/vYqKbvd"
        }
      ]
    },
    {
      "title": "3 Easy ways to generate HTML element from Javascript",
      "description": "Generate HTML tags from string, template and DOM in JavaScript",
      "image": "/images/3wayhtmlfromstring.jpeg",
      "tags": ["elements", "DOM", "HTML"],
      "urls": [
        {
          "icon": "fab fa-instagram",
          "url": "https://www.instagram.com/reel/C90gUMSAugM/"
        },
        {
          "icon": "fab fa-facebook",
          "url": "https://www.facebook.com/reel/340632232321078"
        },
        {
          "icon": "fab fa-threads",
          "url": "https://www.threads.net/@hacky.js/post/C90hZdCMNr8"
        },
        {
          "icon": "fab fa-youtube",
          "url": "https://youtube.com/shorts/qwg6_Cho43k?feature=share"
        },
        {
          "icon": "fab fa-x-twitter",
          "url": "https://x.com/pr0h0_me/status/1816225684509151731"
        },
        {
          "icon": "fab fa-tiktok",
          "url": "https://www.tiktok.com/@hacky.js/video/7395313583904591110"
        },
        {
          "icon": "fab fa-codepen",
          "url": "https://codepen.io/pr0h0/details/dyBpvYr"
        }
      ]
    },
    {
      "title": "JSON.stringify Secrets: Circular Structures ",
      "description": "Convert any JS Object into a string, even one with a circular structure without throwing an error",
      "image": "/images/jsonCircular.jpeg",
      "tags": ["JSON", "stringify", "circular"],
      "urls": [
        {
          "icon": "fab fa-instagram",
          "url": "https://www.instagram.com/p/C963YOCszvp/"
        },
        {
          "icon": "fab fa-facebook",
          "url": "https://www.facebook.com/reel/468747782630661"
        },
        {
          "icon": "fab fa-threads",
          "url": "https://www.threads.net/@hacky.js/post/C964WXVNUDH"
        },
        {
          "icon": "fab fa-youtube",
          "url": "https://youtube.com/shorts/L4m_nnKvl48"
        },
        {
          "icon": "fab fa-x-twitter",
          "url": "https://x.com/pr0h0_me/status/1817120287210557519"
        },
        {
          "icon": "fab fa-tiktok",
          "url": "https://www.tiktok.com/@hacky.js/video/7396230549699890438"
        },
        {
          "icon": "fab fa-codepen",
          "url": "https://codepen.io/pr0h0/details/BagQRXP"
        }
      ]
    },
    {
      "title": "Unlock the power of Set in JS",
      "description": "Learn about the Set object in JavaScript and how to use it",
      "image": "/images/newSet.png",
      "tags": ["set", "javascript"],
      "urls": [
        {
          "icon": "fab fa-instagram",
          "url": "https://www.instagram.com/p/C9-_UC_NjLg/"
        },
        {
          "icon": "fab fa-facebook",
          "url": "https://www.facebook.com/reel/491923866758501"
        },
        {
          "icon": "fab fa-threads",
          "url": "https://www.threads.net/@hacky.js/post/C9_AVOrNsGR"
        },
        {
          "icon": "fab fa-youtube",
          "url": "https://youtu.be/sEMj2m080mU"
        },
        {
          "icon": "fab fa-x-twitter",
          "url": "https://x.com/pr0h0_me/status/1817700973600497918"
        },
        {
          "icon": "fab fa-tiktok",
          "url": "https://www.tiktok.com/@hacky.js/video/7396825492797754629"
        },
        {
          "icon": "fab fa-codepen",
          "url": "https://codepen.io/pr0h0/details/dyBOajX"
        }
      ]
    },
    {
      "title": "Create quote generator in 30 seconds",
      "description": "Learn how to create a reusable quote generator in 30 seconds using JavaScript",
      "image": "/images/quotegen.png",
      "tags": ["quote", "generator", "javascript"],
      "urls": [
        {
          "icon": "fab fa-instagram",
          "url": "https://www.instagram.com/reel/C-Bb0nFuB0C/"
        },
        {
          "icon": "fab fa-facebook",
          "url": "https://www.facebook.com/reel/1955786191502284"
        },
        {
          "icon": "fab fa-threads",
          "url": "https://www.threads.net/@hacky.js/post/C-EBvVQx8B3"
        },
        {
          "icon": "fab fa-youtube",
          "url": "https://www.youtube.com/shorts/v0sEuuqZbiw"
        },
        {
          "icon": "fab fa-x-twitter",
          "url": "https://x.com/pr0h0_me/status/1818407076651290978"
        },
        {
          "icon": "fab fa-tiktok",
          "url": "https://www.tiktok.com/@hacky.js/video/7397178818194066694"
        },
        {
          "icon": "fab fa-codepen",
          "url": "https://codepen.io/pr0h0/details/PorWGoL"
        }
      ]
    },
    {
      "title": "Promise hack in Javascript, optimise your code performance",
      "description": "Optimise your code performance using Promise hack in JavaScript",
      "image": "/images/promisehack.png",
      "tags": ["promise", "javascript", "performance"],
      "urls": [
        {
          "icon": "fab fa-instagram",
          "url": "https://www.instagram.com/reel/C-ELKI8gO3O/"
        },
        {
          "icon": "fab fa-facebook",
          "url": "https://www.facebook.com/reel/966335681905323"
        },
        {
          "icon": "fab fa-threads",
          "url": "https://www.threads.net/@hacky.js/post/C-EM45HtMO3"
        },
        {
          "icon": "fab fa-youtube",
          "url": "https://youtu.be/vSWHAWzV_O0"
        },
        {
          "icon": "fab fa-x-twitter",
          "url": "https://x.com/pr0h0_me/status/1818431207266291988"
        },
        {
          "icon": "fab fa-tiktok",
          "url": "https://www.tiktok.com/@hacky.js/video/7397573271517957381"
        },
        {
          "icon": "fab fa-codepen",
          "url": "https://codepen.io/pr0h0/details/YzoNdzL"
        }
      ]
    },
    {
      "title": "Finally, ultimate promise hack",
      "description": "Stop duplicating code, start using finally method in promises",
      "image": "/images/promisehack.png",
      "tags": ["promise", "javascript", "finally"],
      "urls": [
        {
          "icon": "fab fa-instagram",
          "url": "https://www.instagram.com/reel/C-GkdYys3Rm/"
        },
        {
          "icon": "fab fa-facebook",
          "url": "https://www.facebook.com/reel/1226353448541347"
        },
        {
          "icon": "fab fa-threads",
          "url": "https://www.threads.net/@hacky.js/post/C-GlSKSuwcZ"
        },
        {
          "icon": "fab fa-youtube",
          "url": "https://youtube.com/shorts/L0Beo54X5Ag"
        },
        {
          "icon": "fab fa-x-twitter",
          "url": "https://x.com/pr0h0_me/status/1818767576287285516"
        },
        {
          "icon": "fab fa-tiktok",
          "url": "https://www.tiktok.com/@hacky.js/video/7397918390003846405"
        },
        {
          "icon": "fab fa-codepen",
          "url": "https://codepen.io/pr0h0/details/gONmrNW"
        }
      ]
    },
    {
      "title": "Create CSS Only theme switch and Checkbox toggle element",
      "description": "Skip javascript with this one and create CSS only theme switch and checkbox toggle element",
      "image": "/images/css-only-theme-switch.png",
      "tags": ["css", "theme", "toggle"],
      "urls": [
        {
          "icon": "fab fa-instagram",
          "url": "https://www.instagram.com/p/C-I9bCbR_YA/"
        },
        {
          "icon": "fab fa-facebook",
          "url": "https://www.facebook.com/reel/1529830361253160"
        },
        {
          "icon": "fab fa-threads",
          "url": "https://www.threads.net/@hacky.js/post/C-I_NvVsgkv"
        },
        {
          "icon": "fab fa-youtube",
          "url": "https://youtube.com/shorts/AEu3Csy1S3s"
        },
        {
          "icon": "fab fa-x-twitter",
          "url": "https://x.com/pr0h0_me/status/1819105779389182005"
        },
        {
          "icon": "fab fa-tiktok",
          "url": "https://www.tiktok.com/@hacky.js/video/7398263157833092358"
        },
        {
          "icon": "fab fa-codepen",
          "url": "https://codepen.io/pr0h0/details/zYVZawL"
        }
      ]
    },
    {
      "title": "Create CSS Only tooltip",
      "description": "Skip javascript with this one and create CSS only tooltip",
      "image": "/images/css-only-tooltip.png",
      "tags": ["css", "tooltip", "hover"],
      "urls": [
        {
          "icon": "fab fa-instagram",
          "url": "https://www.instagram.com/p/C-LJrO9MjTh/"
        },
        {
          "icon": "fab fa-facebook",
          "url": "https://www.facebook.com/reel/1001998431371982"
        },
        {
          "icon": "fab fa-threads",
          "url": "https://www.threads.net/@hacky.js/post/C-LKinoRgjZ"
        },
        {
          "icon": "fab fa-youtube",
          "url": "https://youtube.com/shorts/BU4u7oFUVlU"
        },
        {
          "icon": "fab fa-x-twitter",
          "url": "https://x.com/pr0h0_me/status/1819412137497723011"
        },
        {
          "icon": "fab fa-tiktok",
          "url": "https://www.tiktok.com/@hacky.js/video/7398578049232538885"
        },
        {
          "icon": "fab fa-codepen",
          "url": "https://codepen.io/pr0h0/details/MWMmWez"
        }
      ]
    },
    {
      "title": "Create stunning scroll-driven animations with a new browser feature using CSS only.",
      "description": "Create amazing scroll animations using only CSS with a new browser feature!",
      "image": "/images/svg-reveal.png",
      "tags": ["css", "scroll driver", "animation"],
      "urls": [
        {
          "icon": "fab fa-instagram",
          "url": "https://www.instagram.com/p/C-OFDW-OpAN/"
        },
        {
          "icon": "fab fa-facebook",
          "url": "https://www.facebook.com/reel/1139431587358372"
        },
        {
          "icon": "fab fa-threads",
          "url": "https://www.threads.net/@hacky.js/post/C-OHZ4FgJXr"
        },
        {
          "icon": "fab fa-youtube",
          "url": "https://youtube.com/shorts/H4H-qYeit7s"
        },
        {
          "icon": "fab fa-x-twitter",
          "url": "https://x.com/pr0h0_me/status/1819827506494550224"
        },
        {
          "icon": "fab fa-tiktok",
          "url": "https://www.tiktok.com/@hacky.js/video/7399000359642926341"
        },
        {
          "icon": "fab fa-codepen",
          "url": "https://codepen.io/pr0h0/details/ZEdKyNg"
        }
      ]
    }
  ]
}
